IF:ID/IF:ID.v
module IFID(
    CLK,
    InPC,
    InInst,
    PC,
    Inst
);

input CLK;
input [31:0] InPC;
input [31:0] InInst;
output reg [31:0] PC;
output reg [31:0] Inst;

always @(posedge CLK) begin
    PC <= InPC;
    Inst <= InInst;
end

endmodule

IF:ID/IMEM.v
module IMEM(
    ADDR_IN_ROM,
    Inst
);

input wire [31:0] ADDR_IN_ROM;
output reg [31:0] Inst;

always @* begin
case(ADDR_IN_ROM) 
32'h0:  Inst <= 32'h14;
32'h4:  Inst <= 32'h10;
32'h8:  Inst <= 32'h11;
32'hC: Inst <= 32'h100;
default:Inst <= 32'h0;
endcase
end

endmodule

IF:ID/PC/PCAdder.v
module PCAdder(
    PC,
    PCIN
);
input [31:0] PC;
output wire [31:0] PCIN;

assign PCIN = PC + 32'h4;

endmodule

IF:ID/PC/PC.v
//Module
module PC(CLK,RSTB,PCIN,CNTEN,ADDR_OUT_ROM); 
    input CLK,RSTB,CNTEN;
    input [31:0] PCIN;
    output [31:0] ADDR_OUT_ROM;
    reg [31:0] ADDR_OUT_ROM;
    
    always @(posedge CLK) begin
        if      (RSTB==1'b0)    ADDR_OUT_ROM <= 32'h0;
        else    ADDR_OUT_ROM <= PCIN;   
    end
endmodule

IF:ID/PC/PCmux.v
module PCmux(
    PC,
    JumporBranch,
    PCsel,
    PCIN
);
    input wire [31:0] PC;
    input wire [31:0] JumporBranch;
    input wire PCsel; 
    output reg [31:0] PCIN;

    always @* begin
    case(PCsel)
        1'b0:  PCIN <= PC;
        1'b1:  PCIN <= JumporBranch;
        default:PCIN <= PC;
    endcase
    end

endmodule

IF:ID/IF:ID_test.v
module test_IFID();

reg CLK;
reg RSTB,CNTEN;
reg PCsel;
wire [31:0] PCIN;
wire [31:0] PCAdderOUT;
wire [31:0] ADDR_OUT_ROM;
wire [31:0] Inst;

wire [31:0] IFIDOUTPC;
wire [31:0] IFIDOUTInst;

PCmux PCmux(.PCsel(PCsel),.PC(PCAdderOUT),.PCIN(PCIN));
PC PC(.CLK(CLK),.RSTB(RSTB),.CNTEN(CNTEN),.PCIN(PCIN),.ADDR_OUT_ROM(ADDR_OUT_ROM));
PCAdder PCAdder(.PC(ADDR_OUT_ROM),.PCIN(PCAdderOUT));
IMEM IMEM(.ADDR_IN_ROM(ADDR_OUT_ROM),.Inst(Inst));
IFID IFID(.CLK(CLK),.InPC(PCIN),.InInst(Inst),.PC(IFIDOUTPC),.Inst(IFIDOUTInst));

    always begin
    #10 CLK <= ~CLK;
    end

    initial begin
    #0  CLK <= 1'b0;
        CNTEN <= 1'b0;
        PCsel <= 1'b0;
    #10 RSTB <= 1'b0;
    #10 RSTB <= 1'b1;
        CNTEN <= 1'b1;
    #500    $finish;
    end

  initial begin
      $dumpfile("PC_IFID.vcd");
      $dumpvars(0, test_IFID);
  end

  endmodule

IF:ID/PC/PC_IFID.vcd
$date
	Sun Apr  3 15:03:30 2022
$end
$version
	Icarus Verilog
$end
$timescale
	1s
$end
$scope module test_IFID $end
$var wire 32 ! PCIN [31:0] $end
$var wire 32 " PCAdderOUT [31:0] $end
$var wire 32 # Inst [31:0] $end
$var wire 32 $ IFIDOUTPC [31:0] $end
$var wire 32 % IFIDOUTInst [31:0] $end
$var wire 32 & ADDR_OUT_ROM [31:0] $end
$var reg 1 ' CLK $end
$var reg 1 ( CNTEN $end
$var reg 1 ) PCsel $end
$var reg 1 * RSTB $end
$scope module IFID $end
$var wire 1 ' CLK $end
$var wire 32 + InPC [31:0] $end
$var wire 32 , InInst [31:0] $end
$var reg 32 - Inst [31:0] $end
$var reg 32 . PC [31:0] $end
$upscope $end
$scope module IMEM $end
$var wire 32 / ADDR_IN_ROM [31:0] $end
$var reg 32 0 Inst [31:0] $end
$upscope $end
$scope module PC $end
$var wire 1 ' CLK $end
$var wire 1 ( CNTEN $end
$var wire 1 * RSTB $end
$var wire 32 1 PCIN [31:0] $end
$var reg 32 2 ADDR_OUT_ROM [31:0] $end
$upscope $end
$scope module PCAdder $end
$var wire 32 3 PC [31:0] $end
$var wire 32 4 PCIN [31:0] $end
$upscope $end
$scope module PCmux $end
$var wire 32 5 JumporBranch [31:0] $end
$var wire 32 6 PC [31:0] $end
$var wire 1 ) PCsel $end
$var reg 32 7 PCIN [31:0] $end
$upscope $end
$upscope $end
$enddefinitions $end
#0
$dumpvars
bx 7
bx 6
bz 5
bx 4
bx 3
bx 2
bx 1
bx 0
bx /
bx .
bx -
bx ,
bx +
x*
0)
0(
0'
bx &
bx %
bx $
bx #
bx "
bx !
$end
#10
b100 !
b100 +
b100 1
b100 7
b10100 #
b10100 ,
b10100 0
b100 "
b100 4
b100 6
b0 &
b0 /
b0 2
b0 3
0*
1'
#20
1(
1*
0'
#30
b1000 !
b1000 +
b1000 1
b1000 7
b10000 #
b10000 ,
b10000 0
b10100 %
b10100 -
b100 $
b100 .
b1000 "
b1000 4
b1000 6
b100 &
b100 /
b100 2
b100 3
1'
#40
0'
#50
b1100 !
b1100 +
b1100 1
b1100 7
b10001 #
b10001 ,
b10001 0
b1100 "
b1100 4
b1100 6
b1000 &
b1000 /
b1000 2
b1000 3
b10000 %
b10000 -
b1000 $
b1000 .
1'
#60
0'
#70
b10000 !
b10000 +
b10000 1
b10000 7
b100000000 #
b100000000 ,
b100000000 0
b10001 %
b10001 -
b1100 $
b1100 .
b10000 "
b10000 4
b10000 6
b1100 &
b1100 /
b1100 2
b1100 3
1'
#80
0'
#90
b10100 !
b10100 +
b10100 1
b10100 7
b0 #
b0 ,
b0 0
b10100 "
b10100 4
b10100 6
b10000 &
b10000 /
b10000 2
b10000 3
b100000000 %
b100000000 -
b10000 $
b10000 .
1'
#100
0'
#110
b11000 !
b11000 +
b11000 1
b11000 7
b0 %
b0 -
b10100 $
b10100 .
b11000 "
b11000 4
b11000 6
b10100 &
b10100 /
b10100 2
b10100 3
1'
#120
0'
#130
b11100 !
b11100 +
b11100 1
b11100 7
b11100 "
b11100 4
b11100 6
b11000 &
b11000 /
b11000 2
b11000 3
b11000 $
b11000 .
1'
#140
0'
#150
b100000 !
b100000 +
b100000 1
b100000 7
b11100 $
b11100 .
b100000 "
b100000 4
b100000 6
b11100 &
b11100 /
b11100 2
b11100 3
1'
#160
0'
#170
b100100 !
b100100 +
b100100 1
b100100 7
b100100 "
b100100 4
b100100 6
b100000 &
b100000 /
b100000 2
b100000 3
b100000 $
b100000 .
1'
#180
0'
#190
b101000 !
b101000 +
b101000 1
b101000 7
b100100 $
b100100 .
b101000 "
b101000 4
b101000 6
b100100 &
b100100 /
b100100 2
b100100 3
1'
#200
0'
#210
b101100 !
b101100 +
b101100 1
b101100 7
b101100 "
b101100 4
b101100 6
b101000 &
b101000 /
b101000 2
b101000 3
b101000 $
b101000 .
1'
#220
0'
#230
b110000 !
b110000 +
b110000 1
b110000 7
b101100 $
b101100 .
b110000 "
b110000 4
b110000 6
b101100 &
b101100 /
b101100 2
b101100 3
1'
#240
0'
#250
b110100 !
b110100 +
b110100 1
b110100 7
b110100 "
b110100 4
b110100 6
b110000 &
b110000 /
b110000 2
b110000 3
b110000 $
b110000 .
1'
#260
0'
#270
b111000 !
b111000 +
b111000 1
b111000 7
b110100 $
b110100 .
b111000 "
b111000 4
b111000 6
b110100 &
b110100 /
b110100 2
b110100 3
1'
#280
0'
#290
b111100 !
b111100 +
b111100 1
b111100 7
b111100 "
b111100 4
b111100 6
b111000 &
b111000 /
b111000 2
b111000 3
b111000 $
b111000 .
1'
#300
0'
#310
b1000000 !
b1000000 +
b1000000 1
b1000000 7
b111100 $
b111100 .
b1000000 "
b1000000 4
b1000000 6
b111100 &
b111100 /
b111100 2
b111100 3
1'
#320
0'
#330
b1000100 !
b1000100 +
b1000100 1
b1000100 7
b1000100 "
b1000100 4
b1000100 6
b1000000 &
b1000000 /
b1000000 2
b1000000 3
b1000000 $
b1000000 .
1'
#340
0'
#350
b1001000 !
b1001000 +
b1001000 1
b1001000 7
b1000100 $
b1000100 .
b1001000 "
b1001000 4
b1001000 6
b1000100 &
b1000100 /
b1000100 2
b1000100 3
1'
#360
0'
#370
b1001100 !
b1001100 +
b1001100 1
b1001100 7
b1001100 "
b1001100 4
b1001100 6
b1001000 &
b1001000 /
b1001000 2
b1001000 3
b1001000 $
b1001000 .
1'
#380
0'
#390
b1010000 !
b1010000 +
b1010000 1
b1010000 7
b1001100 $
b1001100 .
b1010000 "
b1010000 4
b1010000 6
b1001100 &
b1001100 /
b1001100 2
b1001100 3
1'
#400
0'
#410
b1010100 !
b1010100 +
b1010100 1
b1010100 7
b1010100 "
b1010100 4
b1010100 6
b1010000 &
b1010000 /
b1010000 2
b1010000 3
b1010000 $
b1010000 .
1'
#420
0'
#430
b1011000 !
b1011000 +
b1011000 1
b1011000 7
b1010100 $
b1010100 .
b1011000 "
b1011000 4
b1011000 6
b1010100 &
b1010100 /
b1010100 2
b1010100 3
1'
#440
0'
#450
b1011100 !
b1011100 +
b1011100 1
b1011100 7
b1011100 "
b1011100 4
b1011100 6
b1011000 &
b1011000 /
b1011000 2
b1011000 3
b1011000 $
b1011000 .
1'
#460
0'
#470
b1100000 !
b1100000 +
b1100000 1
b1100000 7
b1011100 $
b1011100 .
b1100000 "
b1100000 4
b1100000 6
b1011100 &
b1011100 /
b1011100 2
b1011100 3
1'
#480
0'
#490
b1100100 !
b1100100 +
b1100100 1
b1100100 7
b1100100 "
b1100100 4
b1100100 6
b1100000 &
b1100000 /
b1100000 2
b1100000 3
b1100000 $
b1100000 .
1'
#500
0'
#510
b1101000 !
b1101000 +
b1101000 1
b1101000 7
b1100100 $
b1100100 .
b1101000 "
b1101000 4
b1101000 6
b1100100 &
b1100100 /
b1100100 2
b1100100 3
1'
